{
    "option1" : {
        "name" : "Nürnberg Tours and Travels", 
        "address" : "Burg 17, 90403 Nürnberg",
        "phone" : "+49-92348978910",
        "silver" : {
            "services" : "City Tour & Erlangen Archeological Museum tour", 
            "price" : 35
        }, 
        "gold" : {
            "services" : "City Tour + 3 Museums of choice & Nuremberg Theater guided Tour", 
            "price" : 110
        }
    }, 
    "option2" : {
        "name" : "Kindle Destinations", 
        "address" : "Hauptmarkt, 90403 Nürnberg",
        "phone" : "+49-89434678910",
        "silver" : {
            "services" : "City Tour & Erlangen Camp tour", 
            "price" : 45
        }, 
        "gold" : {
            "services" : "City Tour + Erlangen Camp tour (with interiors) & Erlangen Castle tour", 
            "price" : 95
        }  
    }
}